pytexttoimage/__init__.py
pytexttoimage/texttoimage.py
pytexttoimage-0.0.2.dist-info/LICENSE
pytexttoimage-0.0.2.dist-info/METADATA
pytexttoimage-0.0.2.dist-info/WHEEL
pytexttoimage-0.0.2.dist-info/top_level.txt
pytexttoimage-0.0.2.dist-info/RECORD
