Metadata-Version: 2.1
Name: pytexttoimage
Version: 0.0.2
Summary: Package to convert text data into image
Home-page: https://github.com/SKP1535/pytext2image.git
Author: Saurabh Kumar
Author-email: skp1535@gmail.com
License: UNKNOWN
Platform: UNKNOWN
Classifier: Programming Language :: Python :: 3
Classifier: License :: OSI Approved :: MIT License
Classifier: Operating System :: OS Independent
Requires-Python: >=3.6
